joern2sarif/__init__.py
joern2sarif/cli.py
joern2sarif/lib/__init__.py
joern2sarif/lib/config.py
joern2sarif/lib/convert.py
joern2sarif/lib/issue.py
joern2sarif/lib/logger.py
joern2sarif-1.1.12.dist-info/LICENSE
joern2sarif-1.1.12.dist-info/METADATA
joern2sarif-1.1.12.dist-info/WHEEL
joern2sarif-1.1.12.dist-info/entry_points.txt
joern2sarif-1.1.12.dist-info/top_level.txt
joern2sarif-1.1.12.dist-info/RECORD
