Metadata-Version: 2.1
Name: joern2sarif
Version: 1.1.12
Summary: Utility script to convert joern/ocular json output to sarif.
Home-page: https://github.com/joernio/joern2sarif
Author: Prabhu Subramanian
Author-email: prabhu@shiftleft.io
Classifier: Development Status :: 5 - Production/Stable
Classifier: Intended Audience :: Developers
Classifier: Intended Audience :: System Administrators
Classifier: Topic :: Utilities
Classifier: Topic :: Security
Classifier: Programming Language :: Python :: 3.6
Classifier: Programming Language :: Python :: 3.8
Classifier: Programming Language :: Python :: 3.9
Classifier: License :: OSI Approved :: Apache Software License
Classifier: Operating System :: OS Independent
Requires-Python: >=3.6
License-File: LICENSE
Requires-Dist: sarif-om
Requires-Dist: jschema-to-python
Requires-Dist: six
